copypod/__init__.py
copypod/exceptions.py
copypod/kube.py
copypod/main.py
copypod/pod_config.py
copypod-0.5.0.dist-info/METADATA
copypod-0.5.0.dist-info/WHEEL
copypod-0.5.0.dist-info/entry_points.txt
copypod-0.5.0.dist-info/licenses/LICENSE
copypod-0.5.0.dist-info/licenses/NOTICE
copypod-0.5.0.dist-info/RECORD
