Metadata-Version: 2.4
Name: copypod
Version: 0.5.0
Summary: Copy a Kubernetes pod and run commands in its environment
License-Expression: Apache-2.0
License-File: LICENSE
License-File: NOTICE
Author: Jeppe Fihl-Pearson
Author-email: jeppe@memrise.com>
Requires-Python: >= 3.10, < 4
Classifier: Programming Language :: Python :: 3
Classifier: Programming Language :: Python :: 3.10
Classifier: Programming Language :: Python :: 3.11
Classifier: Programming Language :: Python :: 3.12
Classifier: Programming Language :: Python :: 3.13
Classifier: Programming Language :: Python :: 3.14
Requires-Dist: kubernetes (>=35.0.0,<35.1.0)
Project-URL: Repository, https://github.com/Memrise/copypod
